geoaddress/.commands.json
geoaddress/__init__.py
geoaddress/__main__.py
geoaddress/cli.py
geoaddress/helpers.py
geoaddress/commands/__init__.py
geoaddress/commands/autocomplete.py
geoaddress/commands/reverse.py
geoaddress/commands/search.py
geoaddress/providers/geoapify.py
geoaddress/providers/geocode_earth.py
geoaddress/providers/google.py
geoaddress/providers/here.py
geoaddress/providers/locationiq.py
geoaddress/providers/mapbox.py
geoaddress/providers/maps_co.py
geoaddress/providers/nominatim.py
geoaddress/providers/opencage.py
geoaddress/providers/photon.py
geoaddress/providers/base/__init__.py
geoaddress/providers/base/confidence.py
geoaddress/providers/base/relevance.py
geoaddress-0.2.4.dist-info/licenses/LICENSE
geoaddress-0.2.4.dist-info/METADATA
geoaddress-0.2.4.dist-info/WHEEL
geoaddress-0.2.4.dist-info/entry_points.txt
geoaddress-0.2.4.dist-info/top_level.txt
geoaddress-0.2.4.dist-info/RECORD
