Metadata-Version: 2.4
Name: geoaddress
Version: 0.2.4
Summary: Python library for address geocoding and reverse geocoding. Provides a unified interface to multiple geocoding providers (Nominatim, Google Maps, Mapbox, etc.) using ProviderKit for provider management.
Author-email: Hicinformatic <hicinformatic@gmail.com>
License: MIT
Project-URL: Homepage, https://github.com/hicinformatic/python-geoaddress
Project-URL: Repository, https://github.com/hicinformatic/python-geoaddress
Project-URL: Documentation, https://github.com/hicinformatic/python-geoaddress#readme
Project-URL: Issues, https://github.com/hicinformatic/python-geoaddress/issues
Keywords: geocoding,reverse-geocoding,address,geolocation,maps,nominatim,google-maps,mapbox,location,python
Classifier: Development Status :: 4 - Beta
Classifier: Intended Audience :: Developers
Classifier: Programming Language :: Python :: 3
Classifier: Programming Language :: Python :: 3.10
Classifier: Programming Language :: Python :: 3.11
Classifier: Programming Language :: Python :: 3.12
Classifier: Topic :: Software Development :: Libraries :: Python Modules
Classifier: Topic :: Internet :: WWW/HTTP :: Dynamic Content
Classifier: Topic :: Scientific/Engineering :: GIS
Requires-Python: >=3.10
License-File: LICENSE
Requires-Dist: providerkit
Provides-Extra: lint
Requires-Dist: ruff>=0.5.0; extra == "lint"
Requires-Dist: mypy>=1.0.0; extra == "lint"
Requires-Dist: semgrep>=1.0.0; extra == "lint"
Requires-Dist: pylint>=3.0.0; extra == "lint"
Provides-Extra: quality
Requires-Dist: radon>=6.0.0; extra == "quality"
Requires-Dist: vulture>=2.0.0; extra == "quality"
Requires-Dist: autoflake>=2.0.0; extra == "quality"
Provides-Extra: security
Requires-Dist: bandit>=1.7.0; extra == "security"
Requires-Dist: safety>=3.0.0; extra == "security"
Requires-Dist: pip-audit>=2.7.0; extra == "security"
Requires-Dist: semgrep>=1.0.0; extra == "security"
Provides-Extra: test
Requires-Dist: pytest>=8.3.0; extra == "test"
Requires-Dist: pytest-cov>=4.1.0; extra == "test"
Requires-Dist: pytest-xdist>=3.5.0; extra == "test"
Dynamic: license-file
